README.rst
setup.py
docs/HISTORY.txt
docs/INSTALL.txt
docs/LICENSE.GPL
docs/LICENSE.txt
jarn/__init__.py
jarn.xmpp.collaboration.egg-info/PKG-INFO
jarn.xmpp.collaboration.egg-info/SOURCES.txt
jarn.xmpp.collaboration.egg-info/dependency_links.txt
jarn.xmpp.collaboration.egg-info/entry_points.txt
jarn.xmpp.collaboration.egg-info/namespace_packages.txt
jarn.xmpp.collaboration.egg-info/not-zip-safe
jarn.xmpp.collaboration.egg-info/requires.txt
jarn.xmpp.collaboration.egg-info/top_level.txt
jarn/xmpp/__init__.py
jarn/xmpp/collaboration/__init__.py
jarn/xmpp/collaboration/component.py
jarn/xmpp/collaboration/component.zcml
jarn/xmpp/collaboration/configure.zcml
jarn/xmpp/collaboration/dmp.py
jarn/xmpp/collaboration/interfaces.py
jarn/xmpp/collaboration/protocol.py
jarn/xmpp/collaboration/testing.py
jarn/xmpp/collaboration/version.txt
jarn/xmpp/collaboration/adapters/__init__.py
jarn/xmpp/collaboration/adapters/atcontenttypes.py
jarn/xmpp/collaboration/adapters/base.py
jarn/xmpp/collaboration/adapters/configure.zcml
jarn/xmpp/collaboration/adapters/dexterity.py
jarn/xmpp/collaboration/adapters/unlock.py
jarn/xmpp/collaboration/browser/__init__.py
jarn/xmpp/collaboration/browser/collaborate.py
jarn/xmpp/collaboration/browser/configure.zcml
jarn/xmpp/collaboration/browser/css/collaborate.css
jarn/xmpp/collaboration/browser/images/save.png
jarn/xmpp/collaboration/browser/js/diff_match_patch.js
jarn/xmpp/collaboration/browser/js/jarnxmpp.collaboration.collaborate.js
jarn/xmpp/collaboration/browser/js/jquery.ba-dotimeout.min.js
jarn/xmpp/collaboration/browser/js/jquery.field_selection.js
jarn/xmpp/collaboration/profiles/default/cssregistry.xml
jarn/xmpp/collaboration/profiles/default/jsregistry.xml
jarn/xmpp/collaboration/profiles/default/metadata.xml
jarn/xmpp/collaboration/profiles/default/registry.xml
jarn/xmpp/collaboration/tests/__init__.py
jarn/xmpp/collaboration/tests/mock.py
jarn/xmpp/collaboration/tests/test_atct_adapters.py
jarn/xmpp/collaboration/tests/test_collaborate_view.py
jarn/xmpp/collaboration/tests/test_dexterity_adapters.py
jarn/xmpp/collaboration/tests/test_protocol.py
jarn/xmpp/collaboration/tests/test_protocol_functional.py
jarn/xmpp/collaboration/tests/test_unlock.py