Metadata-Version: 1.0
Name: jarn.xmpp.collaboration
Version: 0.1a4
Summary: Collaborative editing for Plone
Home-page: https://github.com/ggozad/jarn.xmpp.collaboration
Author: Yiorgis Gozadinos
Author-email: ggozad@jarn.com
License: GPL
Platform: UNKNOWN
Classifier: Development Status :: 3 - Alpha
Classifier: Framework :: Plone
Classifier: Intended Audience :: Developers
Classifier: Programming Language :: Python
